operetta/__init__.py
operetta/app.py
operetta/ddd/__init__.py
operetta/ddd/application/__init__.py
operetta/ddd/domain/__init__.py
operetta/ddd/errors.py
operetta/ddd/infrastructure/__init__.py
operetta/ddd/infrastructure/db/__init__.py
operetta/ddd/infrastructure/db/postgres/__init__.py
operetta/ddd/infrastructure/db/postgres/adapters/__init__.py
operetta/ddd/infrastructure/db/postgres/adapters/asyncpg.py
operetta/ddd/infrastructure/db/postgres/adapters/asyncpg_ha.py
operetta/ddd/infrastructure/db/postgres/adapters/interface.py
operetta/ddd/shared/__init__.py
operetta/integrations/__init__.py
operetta/integrations/aiohttp/__init__.py
operetta/integrations/aiohttp/annotations.py
operetta/integrations/aiohttp/config.py
operetta/integrations/aiohttp/errors.py
operetta/integrations/aiohttp/middlewares.py
operetta/integrations/aiohttp/openapi/__init__.py
operetta/integrations/aiohttp/openapi/builder.py
operetta/integrations/aiohttp/openapi/redoc.html
operetta/integrations/aiohttp/openapi/swagger.html
operetta/integrations/aiohttp/providers.py
operetta/integrations/aiohttp/request.py
operetta/integrations/aiohttp/response.py
operetta/integrations/aiohttp/route_processing.py
operetta/integrations/aiohttp/service.py
operetta/integrations/asyncpg/__init__.py
operetta/integrations/asyncpg/config.py
operetta/integrations/asyncpg/providers.py
operetta/integrations/asyncpg/service.py
operetta/integrations/asyncpg_ha/__init__.py
operetta/integrations/asyncpg_ha/config.py
operetta/integrations/asyncpg_ha/providers.py
operetta/integrations/asyncpg_ha/service.py
operetta/integrations/prometheus/__init__.py
operetta/integrations/prometheus/config.py
operetta/integrations/prometheus/providers.py
operetta/integrations/prometheus/service.py
operetta/integrations/sentry/__init__.py
operetta/integrations/sentry/config.py
operetta/integrations/sentry/providers.py
operetta/integrations/sentry/service.py
operetta/py.typed
operetta/service/__init__.py
operetta/service/base.py
operetta-0.0.16.dist-info/METADATA
operetta-0.0.16.dist-info/WHEEL
operetta-0.0.16.dist-info/licenses/LICENSE
operetta-0.0.16.dist-info/licenses/NOTICE
operetta-0.0.16.dist-info/RECORD
