Metadata-Version: 2.4
Name: operetta
Version: 0.0.16
Summary: A lightweight framework for building Python applications that is not tied to a specific transport protocol
License: Apache-2.0
License-File: LICENSE
License-File: NOTICE
Keywords: application,framework,ddd,domain-driven design,asyncio,microservices,microservice,dependency-injection,dependency injection,di,web,api,rest,aiohttp,http,openapi,openapi3,swagger,swagger-ui,redoc,postgres,postgresql,database,asyncpg,hasql,aiomisc
Author: Alexander Tikhonov
Author-email: random.gauss@gmail.com
Requires-Python: >=3.11,<4.0
Classifier: Development Status :: 5 - Production/Stable
Classifier: Intended Audience :: Developers
Classifier: License :: OSI Approved :: Apache Software License
Classifier: Operating System :: OS Independent
Classifier: Programming Language :: Python
Classifier: Programming Language :: Python :: 3
Classifier: Programming Language :: Python :: 3 :: Only
Classifier: Programming Language :: Python :: 3.11
Classifier: Programming Language :: Python :: 3.12
Classifier: Programming Language :: Python :: 3.13
Classifier: Programming Language :: Python :: 3.14
Classifier: Programming Language :: Python :: Implementation :: CPython
Classifier: Environment :: Console
Classifier: Environment :: Web Environment
Classifier: Framework :: AsyncIO
Classifier: Typing :: Typed
Classifier: Topic :: Internet :: WWW/HTTP
Classifier: Topic :: Internet :: WWW/HTTP :: HTTP Servers
Classifier: Topic :: Internet :: WWW/HTTP :: Dynamic Content
Classifier: Topic :: Database
Classifier: Topic :: Database :: Front-Ends
Classifier: Topic :: Software Development :: Libraries
Classifier: Topic :: Software Development :: Libraries :: Application Frameworks
Classifier: Topic :: Software Development :: Libraries :: Python Modules
Provides-Extra: aiohttp
Provides-Extra: asyncpg
Provides-Extra: hasql
Provides-Extra: prometheus
Provides-Extra: sentry
Requires-Dist: aiohttp (>=3.12.15,<4.0.0) ; extra == "aiohttp"
Requires-Dist: aiomisc[uvloop] (>=17.9.4,<18.0.0)
Requires-Dist: asyncpg (>=0.30.0,<0.31.0) ; extra == "asyncpg"
Requires-Dist: dishka (>=1.7.1,<2.0.0)
Requires-Dist: hasql (>=0.8.1,<0.9.0) ; extra == "hasql"
Requires-Dist: openapify (>=0.7,<0.8) ; extra == "aiohttp"
Requires-Dist: orjson (>=3.11.3,<4.0.0) ; extra == "aiohttp"
Requires-Dist: prometheus-client (>=0.23.1,<0.24.0) ; extra == "prometheus"
Requires-Dist: pyyaml (>=6.0.2,<7.0.0)
Requires-Dist: sentry-sdk (>=2.41.0,<3.0.0) ; extra == "sentry"
